pacc/__init__.py
pacc/pacc.py
pacc/adb/__init__.py
pacc/adb/adb.py
pacc/adb/ld_adb.py
pacc/adb/ld_console.py
pacc/adb/ld_uia.py
pacc/adb/uia.py
pacc/base/__init__.py
pacc/base/decorator.py
pacc/base/dt.py
pacc/base/print.py
pacc/base/sleep.py
pacc/base/ucc_client.py
pacc/config/__init__.py
pacc/config/config.py
pacc/ld_proj/__init__.py
pacc/ld_proj/idle_fish.py
pacc/ld_proj/ld_proj.py
pacc/mysql/__init__.py
pacc/mysql/create.py
pacc/mysql/mysql.py
pacc/mysql/retrieve.py
pacc/mysql/update.py
pacc/network/__init__.py
pacc/network/sd_spider.py
pacc/network/ucc_server.py
pacc/network/usc_server.py
pacc/project/__init__.py
pacc/project/pdd_video.py
pacc/project/project.py
pacc/project/sd.py
pacc/project/ksjsb/__init__.py
pacc/project/ksjsb/activity.py
pacc/project/ksjsb/ksjsb.py
pacc/project/ksjsb/resource_id.py
pacc/project/qtt/__init__.py
pacc/project/qtt/activity.py
pacc/project/qtt/qtt.py
pacc/project/qtt/resource_id.py
pacc/tools/__init__.py
pacc/tools/captcha.py
pacc/tools/dir.py
pacc/tools/email.py
pacc/tools/file.py
pacc/tools/regular.py
pacc/tools/tools.py
pacc/tools/xml.py
pacc-0.0.606.dist-info/LICENSE
pacc-0.0.606.dist-info/METADATA
pacc-0.0.606.dist-info/WHEEL
pacc-0.0.606.dist-info/top_level.txt
pacc-0.0.606.dist-info/RECORD
