Metadata-Version: 2.1
Name: pacc
Version: 0.0.606
Summary: Python Android Cluster Control 为在Windows上使用Python通过USB（通用串行总线）或WLAN
Home-page: https://github.com/cocos56/pacc
Author: Coco
Author-email: zj175@139.com
License-File: LICENSE
